python_project_alban_magerand_203/__init__.py
python_project_alban_magerand_203/backtest.py
python_project_alban_magerand_203/blockchain/backtest.pkl
python_project_alban_magerand_203/blockchain/dash_backtest.pkl
python_project_alban_magerand_203/blockchain/test.pkl
python_project_alban_magerand_203/dash_app.py
python_project_alban_magerand_203/portfolio.py
python_project_alban_magerand_203/python_project_alban_magerand_203.py
python_project_alban_magerand_203/transaction_logs/AmberFalconLawyer.parquet
python_project_alban_magerand_203/transaction_logs/AmberSharkMechanic.parquet
python_project_alban_magerand_203/transaction_logs/AmberWolfSoldier.parquet
python_project_alban_magerand_203/transaction_logs/BlackHawkFarmer.parquet
python_project_alban_magerand_203/transaction_logs/BrownWolfArchitect.parquet
python_project_alban_magerand_203/transaction_logs/CrimsonOwlMechanic.parquet
python_project_alban_magerand_203/transaction_logs/GreenBearPhotographer.parquet
python_project_alban_magerand_203/transaction_logs/GreyCobraPilot.parquet
python_project_alban_magerand_203/transaction_logs/MagentaLynxPlumber.parquet
python_project_alban_magerand_203/transaction_logs/PinkElephantBlacksmith.parquet
python_project_alban_magerand_203/transaction_logs/PurpleJaguarPhotographer.parquet
python_project_alban_magerand_203/transaction_logs/RedLionSoldier.parquet
python_project_alban_magerand_203/transaction_logs/SilverFoxPlumber.parquet
python_project_alban_magerand_203/transaction_logs/SilverTigerTailor.parquet
python_project_alban_magerand_203/transaction_logs/VioletGorillaFirefighter.parquet
python_project_alban_magerand_203/transaction_logs/WhiteOwlBlacksmith.parquet
python_project_alban_magerand_203/transaction_logs/YellowEagleTeacher.parquet
python_project_alban_magerand_203/transaction_logs/YellowFoxPhotographer.parquet
python_project_alban_magerand_203/utils.py
python_project_alban_magerand_203-0.0.6.dist-info/LICENSE
python_project_alban_magerand_203-0.0.6.dist-info/METADATA
python_project_alban_magerand_203-0.0.6.dist-info/WHEEL
python_project_alban_magerand_203-0.0.6.dist-info/RECORD
